<?xml version="1.0" ?>
<DIRETORIO_DE_GRUPOS>
   <GRUPO_DE_PESQUISA>
      <NOME>Alimentação Saudável em Areas Urbanase Rurais - ASUR</NOME>
      <IDENTIFICACAO_DGP>8131893720209175</IDENTIFICACAO_DGP>
      <REPERCUSSAO>O grupo trabalha dinamicas de arranjos produtivos locais e meio ambiente territorial. Hoje, o IPA dispõe de dados de perfil e de percurso de produtores em areas rurais e urbanas do Estado. A complexidade ligada à gestão destas áreas, apresenta bases de inovação cientifica, políticas e social (novas práticas de apropriação, novos atores coletivos, etc). Trata-se de regiões que aparecem como espaços de inovação e reinvenção dos bens comuns. Observa-se mudanças no modo de vida das populações locais com tendências à melhoria da autonomia e segurança alimentar, de novas formas de mercado (circuitos curtos) de conservação, preservação e/ou recuperação do bioma. O conjunto destas questões levou o grupo a trabalhar com o conceito de justiça ambiental envolvendo aspectos como acesso e gestão de recursos naturais; normas de produção, melhoria na qualidade e identificação territoral dos produtos, preservação da biodiversidade.</REPERCUSSAO>
      <AREA>Ciências Humanas; Sociologia</AREA>
      <INSTITUICAO>Instituto Agronômico de Pernambuco - IPA</INSTITUICAO>
      <ANO_FORMACAO>2015</ANO_FORMACAO>
      <ENDERECO>
         <CEP>50761000</CEP>
         <LOCALIDADE>Recife</LOCALIDADE>
         <UF>PE</UF>
         <BAIRRO>Jiquiá</BAIRRO>
         <COMPLEMENTO>bloco 10; sala 17</COMPLEMENTO>
         <NUMERO>1371</NUMERO>
         <LOGRADOURO>Avenida General San Martin - de 1209/1210 ao fim</LOGRADOURO>
      </ENDERECO>
      <PESQUISADORES>
         <PESQUISADOR NOME="Alexandre Hugo Cezar Barros" LATTES="7312779971785780" FORMACAO_ACADEMICA="Doutorado" CATEGORIA="PESQUISADOR">
            <AREA>Agrometeorologia</AREA>
            <AREA>Aspectos Físico-Ambientais do Planejamento Urbano e Regional</AREA>
            <AREA>Conservação de Solo e Água</AREA>
            <AREA>Física do Solo</AREA>
            <AREA>Meteorologia</AREA>
            <AREA>Modelagem Agrometeorológica</AREA>
            <GRUPO_DE_PESQUISA>Alimentação Saudável em Areas Urbanase Rurais - ASUR</GRUPO_DE_PESQUISA>
            <LINHA_DE_PESQUISA>Pesquisa-ação interdisciplinar e multi-atores</LINHA_DE_PESQUISA>
         </PESQUISADOR>
         <PESQUISADOR NOME="Ana Luiza du Bocage Neta" LATTES="8131729601512938" FORMACAO_ACADEMICA="Doutorado" CATEGORIA="PESQUISADOR">
            <AREA>Taxonomia de Fanerógamos</AREA>
            <GRUPO_DE_PESQUISA>BOTÂNICA</GRUPO_DE_PESQUISA>
            <GRUPO_DE_PESQUISA>Alimentação Saudável em Areas Urbanase Rurais - ASUR</GRUPO_DE_PESQUISA>
            <LINHA_DE_PESQUISA>Pesquisa-ação interdisciplinar e multi-atores</LINHA_DE_PESQUISA>
            <LINHA_DE_PESQUISA>Plantas invasoras de cultivos</LINHA_DE_PESQUISA>
            <LINHA_DE_PESQUISA>Floras regionais</LINHA_DE_PESQUISA>
            <LINHA_DE_PESQUISA>Forrageiras nativas</LINHA_DE_PESQUISA>
         </PESQUISADOR>
         <PESQUISADOR NOME="Anália Carmem Silva de Almeida" LATTES="4154068579274176" FORMACAO_ACADEMICA="Doutorado" CATEGORIA="PESQUISADOR">
            <AREA>Ecologia de Ecossistemas</AREA>
            <AREA>ENGENHARIA DE SEGURANÇA DO TRABALHO</AREA>
            <AREA>Manejo Florestal</AREA>
            <AREA>Silvicultura</AREA>
            <GRUPO_DE_PESQUISA>Alimentação Saudável em Areas Urbanase Rurais - ASUR</GRUPO_DE_PESQUISA>
            <LINHA_DE_PESQUISA>Pesquisa-ação interdisciplinar e multi-atores</LINHA_DE_PESQUISA>
         </PESQUISADOR>
         <PESQUISADOR NOME="Cynthia Araújo de Lacerda" LATTES="1950611345328013" FORMACAO_ACADEMICA="Doutorado" CATEGORIA="PESQUISADOR">
            <AREA>controle alternativo de insetos</AREA>
            <AREA>Controle cultural de insetos</AREA>
            <AREA>Entomologia Agrícola</AREA>
            <AREA>Fitossanidade</AREA>
            <AREA>Pesquisa e Desenvolvimento</AREA>
            <GRUPO_DE_PESQUISA>CONTROLE BIOLÓGICO</GRUPO_DE_PESQUISA>
            <GRUPO_DE_PESQUISA>Alimentação Saudável em Areas Urbanase Rurais - ASUR</GRUPO_DE_PESQUISA>
            <GRUPO_DE_PESQUISA>Entomologia Agrícola</GRUPO_DE_PESQUISA>
            <GRUPO_DE_PESQUISA>Groupe d'Etudes Petites Paysanneries -Latino Americain (GPP/Latino)</GRUPO_DE_PESQUISA>
            <GRUPO_DE_PESQUISA>HORTALIÇAS</GRUPO_DE_PESQUISA>
            <LINHA_DE_PESQUISA>Fitossanidade</LINHA_DE_PESQUISA>
            <LINHA_DE_PESQUISA>Interdisciplinar em ciências sociais, biológicas e ambientais</LINHA_DE_PESQUISA>
            <LINHA_DE_PESQUISA>controle alternativo</LINHA_DE_PESQUISA>
            <LINHA_DE_PESQUISA>Pesquisa-ação interdisciplinar e multi-atores</LINHA_DE_PESQUISA>
            <LINHA_DE_PESQUISA>Manejo integrado de pragas</LINHA_DE_PESQUISA>
            <LINHA_DE_PESQUISA>Controle biológico</LINHA_DE_PESQUISA>
            <LINHA_DE_PESQUISA>Criação massal de crisopídeos para controle de pragas de citros e da palma forrageira</LINHA_DE_PESQUISA>
            <LINHA_DE_PESQUISA>Controle biológico com predadores</LINHA_DE_PESQUISA>
            <LINHA_DE_PESQUISA>Manejo Integrado de Insetos-Pragas</LINHA_DE_PESQUISA>
         </PESQUISADOR>
         <PESQUISADOR NOME="Eliane de CARVALHO NOYA" LATTES="7090328055126677" FORMACAO_ACADEMICA="Doutorado" CATEGORIA="LIDER">
            <AREA>Agricultura Familiar Sociedade e Mundialização</AREA>
            <AREA>Desenvolvimento Rural Sustentavel</AREA>
            <AREA>Economias Agrária e dos Recursos Naturais</AREA>
            <AREA>Inovação e Mudanças Sociais</AREA>
            <AREA>Metodologia de Pesquisa</AREA>
            <AREA>Multifuncionalidade da Agricultura</AREA>
            <GRUPO_DE_PESQUISA>SOCIOECONOMIA</GRUPO_DE_PESQUISA>
            <GRUPO_DE_PESQUISA>Alimentação Saudável em Areas Urbanase Rurais - ASUR</GRUPO_DE_PESQUISA>
            <GRUPO_DE_PESQUISA>Groupe d'Etudes Petites Paysanneries -Latino Americain (GPP/Latino)</GRUPO_DE_PESQUISA>
            <GRUPO_DE_PESQUISA>HORTALIÇAS</GRUPO_DE_PESQUISA>
            <LINHA_DE_PESQUISA>Análises econômicas ex-ant e ex-post de projetos de pesquisa e desenvolvimento</LINHA_DE_PESQUISA>
            <LINHA_DE_PESQUISA>Análise socioeconômica dos resultados da pesquisa agropecuária</LINHA_DE_PESQUISA>
            <LINHA_DE_PESQUISA>Desenvolvimento rural: difusão de inovações/história, antropologia, sociologia e etnografia</LINHA_DE_PESQUISA>
            <LINHA_DE_PESQUISA>Interdisciplinar em ciências sociais, biológicas e ambientais</LINHA_DE_PESQUISA>
            <LINHA_DE_PESQUISA>Prospecção de demandas tecnológicas</LINHA_DE_PESQUISA>
            <LINHA_DE_PESQUISA>Proposição de projetos, ações políticas para intervenções tecnológicas</LINHA_DE_PESQUISA>
            <LINHA_DE_PESQUISA>Pesquisa-ação interdisciplinar e multi-atores</LINHA_DE_PESQUISA>
            <LINHA_DE_PESQUISA>Estudos sobre modernização institucional</LINHA_DE_PESQUISA>
            <LINHA_DE_PESQUISA>Estudos de cadeias produtivas</LINHA_DE_PESQUISA>
         </PESQUISADOR>
         <PESQUISADOR NOME="Eline Waked Ferreira Gomes" LATTES="3160652539662734" FORMACAO_ACADEMICA="Doutorado" CATEGORIA="PESQUISADOR">
            <AREA>Botânica</AREA>
            <AREA>Educação Ambiental</AREA>
            <AREA>Fisiologia de Plantas Cultivadas</AREA>
            <AREA>Floricultura</AREA>
            <AREA>Meio Ambiente</AREA>
            <AREA>Metodologia Científica e Técnicas de Pesquisa</AREA>
            <GRUPO_DE_PESQUISA>Alimentação Saudável em Areas Urbanase Rurais - ASUR</GRUPO_DE_PESQUISA>
            <LINHA_DE_PESQUISA>Pesquisa-ação interdisciplinar e multi-atores</LINHA_DE_PESQUISA>
         </PESQUISADOR>
         <PESQUISADOR NOME="Enildo Cardoso" LATTES="7044406727339547" FORMACAO_ACADEMICA="Graduação" CATEGORIA="PESQUISADOR">
            <AREA>Extensão Rural</AREA>
            <AREA>Fertilidade do Solo e Adubação</AREA>
            <AREA>Fitopatologia</AREA>
            <AREA>Irrigação e Drenagem</AREA>
            <AREA>Manejo e Conservação do Solo</AREA>
            <AREA>Produção de Mudas</AREA>
            <GRUPO_DE_PESQUISA>Alimentação Saudável em Areas Urbanase Rurais - ASUR</GRUPO_DE_PESQUISA>
            <LINHA_DE_PESQUISA>Pesquisa-ação interdisciplinar e multi-atores</LINHA_DE_PESQUISA>
         </PESQUISADOR>
         <PESQUISADOR NOME="Francinete Francis Lacerda" LATTES="8295605388508449" FORMACAO_ACADEMICA="Doutorado" CATEGORIA="PESQUISADOR">
            <AREA>Agroecologia</AREA>
            <AREA>Climatologia</AREA>
            <AREA>Mudanças Climáticas</AREA>
            <GRUPO_DE_PESQUISA>Alimentação Saudável em Areas Urbanase Rurais - ASUR</GRUPO_DE_PESQUISA>
            <GRUPO_DE_PESQUISA>Groupe d'Etudes Petites Paysanneries -Latino Americain (GPP/Latino)</GRUPO_DE_PESQUISA>
            <LINHA_DE_PESQUISA>Interdisciplinar em ciências sociais, biológicas e ambientais</LINHA_DE_PESQUISA>
            <LINHA_DE_PESQUISA>Pesquisa-ação interdisciplinar e multi-atores</LINHA_DE_PESQUISA>
         </PESQUISADOR>
         <PESQUISADOR NOME="Geraldo Majella Bezerra Lopes" LATTES="6293886032778885" FORMACAO_ACADEMICA="Doutorado" CATEGORIA="LIDER">
            <AREA>Planejamento e Desenvolvimento de Sistemas Agropecuários</AREA>
            <AREA>Planejamento em Ciência e Tecnologia</AREA>
            <GRUPO_DE_PESQUISA>ZONEAMENTO AGROECOLÓGICO DE PERNAMBUCO</GRUPO_DE_PESQUISA>
            <GRUPO_DE_PESQUISA>FRUTICULTURA</GRUPO_DE_PESQUISA>
            <GRUPO_DE_PESQUISA>SOCIOECONOMIA</GRUPO_DE_PESQUISA>
            <GRUPO_DE_PESQUISA>Alimentação Saudável em Areas Urbanase Rurais - ASUR</GRUPO_DE_PESQUISA>
            <GRUPO_DE_PESQUISA>Groupe d'Etudes Petites Paysanneries -Latino Americain (GPP/Latino)</GRUPO_DE_PESQUISA>
            <GRUPO_DE_PESQUISA>Geotecnologia Agrícola e Investigação Ambiental - GAIA</GRUPO_DE_PESQUISA>
            <GRUPO_DE_PESQUISA>HORTALIÇAS</GRUPO_DE_PESQUISA>
            <LINHA_DE_PESQUISA>Análises econômicas ex-ant e ex-post de projetos de pesquisa e desenvolvimento</LINHA_DE_PESQUISA>
            <LINHA_DE_PESQUISA>Análise socioeconômica dos resultados da pesquisa agropecuária</LINHA_DE_PESQUISA>
            <LINHA_DE_PESQUISA>Desenvolvimento rural: difusão de inovações/história, antropologia, sociologia e etnografia</LINHA_DE_PESQUISA>
            <LINHA_DE_PESQUISA>Melhoramento e propagação de fruteiras tropicais</LINHA_DE_PESQUISA>
            <LINHA_DE_PESQUISA>Interdisciplinar em ciências sociais, biológicas e ambientais</LINHA_DE_PESQUISA>
            <LINHA_DE_PESQUISA>Prospecção de demandas tecnológicas</LINHA_DE_PESQUISA>
            <LINHA_DE_PESQUISA>Proposição de projetos, ações políticas para intervenções tecnológicas</LINHA_DE_PESQUISA>
            <LINHA_DE_PESQUISA>Pesquisa-ação interdisciplinar e multi-atores</LINHA_DE_PESQUISA>
            <LINHA_DE_PESQUISA>Zoneamento Ambiental</LINHA_DE_PESQUISA>
            <LINHA_DE_PESQUISA>Estudos sobre modernização institucional</LINHA_DE_PESQUISA>
            <LINHA_DE_PESQUISA>Agricultura e Produção Sustentável</LINHA_DE_PESQUISA>
            <LINHA_DE_PESQUISA>Estudos de cadeias produtivas</LINHA_DE_PESQUISA>
         </PESQUISADOR>
         <PESQUISADOR NOME="Jose Nildo Tabosa" LATTES="7594047791205484" FORMACAO_ACADEMICA="Doutorado" CATEGORIA="PESQUISADOR">
            <AREA>Aplicação de Radioisótopos na Agricultura</AREA>
            <AREA>Avaliação, Produção e Conservação de Forragens</AREA>
            <AREA>Fisiologia de Plantas Forrageiras</AREA>
            <AREA>Melhoramento Vegetal</AREA>
            <AREA>SOLOS SALINOS</AREA>
            <AREA>Zoneamento de Risco Climático</AREA>
            <GRUPO_DE_PESQUISA>RADIOECOLOGIA (RAE)</GRUPO_DE_PESQUISA>
            <GRUPO_DE_PESQUISA>CEREAIS, RAÍZES, TUBÉRCULOS E SORGO DE DUPLA FINALIDADE</GRUPO_DE_PESQUISA>
            <GRUPO_DE_PESQUISA>Agropecuária e Biotecnologia</GRUPO_DE_PESQUISA>
            <GRUPO_DE_PESQUISA>Alimentação Saudável em Areas Urbanase Rurais - ASUR</GRUPO_DE_PESQUISA>
            <GRUPO_DE_PESQUISA>Fitovirologia</GRUPO_DE_PESQUISA>
            <LINHA_DE_PESQUISA>Manejo de caprinos e ovinos</LINHA_DE_PESQUISA>
            <LINHA_DE_PESQUISA>Radioecologia</LINHA_DE_PESQUISA>
            <LINHA_DE_PESQUISA>Semioquímicos</LINHA_DE_PESQUISA>
            <LINHA_DE_PESQUISA>Pesquisa-ação interdisciplinar e multi-atores</LINHA_DE_PESQUISA>
            <LINHA_DE_PESQUISA>Desenvolvimento, introdução e avaliação agronômica de genótipos de inhame para o Estado de Pernambuco</LINHA_DE_PESQUISA>
            <LINHA_DE_PESQUISA>Melhoramento Vegetal</LINHA_DE_PESQUISA>
            <LINHA_DE_PESQUISA>Avaliação e Caracterização Vegetal</LINHA_DE_PESQUISA>
            <LINHA_DE_PESQUISA>Manejo Animal</LINHA_DE_PESQUISA>
         </PESQUISADOR>
         <PESQUISADOR NOME="Jose Nunes Filho" LATTES="4822775251456662" FORMACAO_ACADEMICA="Doutorado" CATEGORIA="PESQUISADOR">
            <AREA>Ciência do Solo</AREA>
            <AREA>Ciências Agrárias</AREA>
            <AREA>Irrigação e Drenagem</AREA>
            <GRUPO_DE_PESQUISA>Alimentação Saudável em Areas Urbanase Rurais - ASUR</GRUPO_DE_PESQUISA>
            <LINHA_DE_PESQUISA>Pesquisa-ação interdisciplinar e multi-atores</LINHA_DE_PESQUISA>
         </PESQUISADOR>
         <PESQUISADOR NOME="Luiz Gonzaga Biones Ferraz" LATTES="3245652236294436" FORMACAO_ACADEMICA="Doutorado" CATEGORIA="PESQUISADOR">
            <AREA>Cultura de Tecidos Vegetais</AREA>
            <AREA>Fitotecnia</AREA>
            <AREA>Genética Vegetal</AREA>
            <AREA>Melhoramento</AREA>
            <AREA>Mutagênese</AREA>
            <AREA>Salinidade</AREA>
            <GRUPO_DE_PESQUISA>FRUTICULTURA</GRUPO_DE_PESQUISA>
            <GRUPO_DE_PESQUISA>Alimentação Saudável em Areas Urbanase Rurais - ASUR</GRUPO_DE_PESQUISA>
            <LINHA_DE_PESQUISA>Melhoramento e propagação de fruteiras tropicais</LINHA_DE_PESQUISA>
            <LINHA_DE_PESQUISA>Pesquisa-ação interdisciplinar e multi-atores</LINHA_DE_PESQUISA>
         </PESQUISADOR>
         <PESQUISADOR NOME="Maria do Socorro Medeiros" LATTES="9573266305715856" FORMACAO_ACADEMICA="Mestrado" CATEGORIA="PESQUISADOR">
            <AREA>Associativismo / Cooperativismo</AREA>
            <AREA>Desenvolvimento Econômico Local Sustentável</AREA>
            <AREA>Economia Agrária</AREA>
            <AREA>Economia Geral</AREA>
            <AREA>Elaboração e Gestão de Projetos</AREA>
            <AREA>Teoria Geral da Economia</AREA>
            <GRUPO_DE_PESQUISA>Alimentação Saudável em Areas Urbanase Rurais - ASUR</GRUPO_DE_PESQUISA>
            <LINHA_DE_PESQUISA>Pesquisa-ação interdisciplinar e multi-atores</LINHA_DE_PESQUISA>
         </PESQUISADOR>
         <PESQUISADOR NOME="Marta Maria Amâncio do Nascimento" LATTES="0556761788039357" FORMACAO_ACADEMICA="Doutorado" CATEGORIA="PESQUISADOR">
            <AREA>Agronomia</AREA>
            <AREA>Biotecnologia Ambiental e Recursos Naturais</AREA>
            <AREA>Divulgação Científica</AREA>
            <AREA>Fisiologia Vegetal</AREA>
            <AREA>Manejo e Tratos Culturais</AREA>
            <AREA>Melhoramento Vegetal</AREA>
            <GRUPO_DE_PESQUISA>CEREAIS, RAÍZES, TUBÉRCULOS E SORGO DE DUPLA FINALIDADE</GRUPO_DE_PESQUISA>
            <GRUPO_DE_PESQUISA>Alimentação Saudável em Areas Urbanase Rurais - ASUR</GRUPO_DE_PESQUISA>
            <LINHA_DE_PESQUISA>Pesquisa-ação interdisciplinar e multi-atores</LINHA_DE_PESQUISA>
            <LINHA_DE_PESQUISA>Biotecnologia e Melhoramento Vegetal</LINHA_DE_PESQUISA>
         </PESQUISADOR>
         <PESQUISADOR NOME="Maviael Fonsêca de Castro" LATTES="1080174084861970" FORMACAO_ACADEMICA="Doutorado" CATEGORIA="PESQUISADOR">
            <AREA>Carcinocultura</AREA>
            <AREA>Ensino Profissionalizante</AREA>
            <AREA>Extensão Rural</AREA>
            <AREA>Fatores Abióticos do Mar</AREA>
            <AREA>Manejo e Conservação de Recursos Pesqueiros Marinhos</AREA>
            <AREA>Maricultura</AREA>
            <GRUPO_DE_PESQUISA>Alimentação Saudável em Areas Urbanase Rurais - ASUR</GRUPO_DE_PESQUISA>
            <GRUPO_DE_PESQUISA>Groupe d'Etudes Petites Paysanneries -Latino Americain (GPP/Latino)</GRUPO_DE_PESQUISA>
            <LINHA_DE_PESQUISA>Interdisciplinar em ciências sociais, biológicas e ambientais</LINHA_DE_PESQUISA>
            <LINHA_DE_PESQUISA>Pesquisa-ação interdisciplinar e multi-atores</LINHA_DE_PESQUISA>
         </PESQUISADOR>
         <PESQUISADOR NOME="Regina Ceres Torres da Rosa" LATTES="0899617096572371" FORMACAO_ACADEMICA="Doutorado" CATEGORIA="PESQUISADOR">
            <AREA>Defesa Fitossanitária</AREA>
            <AREA>Fitopatologia</AREA>
            <AREA>Patologia de Sementes</AREA>
            <GRUPO_DE_PESQUISA>CONTROLE BIOLÓGICO</GRUPO_DE_PESQUISA>
            <GRUPO_DE_PESQUISA>BIOLOGIA DO SOLO</GRUPO_DE_PESQUISA>
            <GRUPO_DE_PESQUISA>Alimentação Saudável em Areas Urbanase Rurais - ASUR</GRUPO_DE_PESQUISA>
            <GRUPO_DE_PESQUISA>HORTALIÇAS</GRUPO_DE_PESQUISA>
            <LINHA_DE_PESQUISA>Fitossanidade</LINHA_DE_PESQUISA>
            <LINHA_DE_PESQUISA>Pesquisa-ação interdisciplinar e multi-atores</LINHA_DE_PESQUISA>
            <LINHA_DE_PESQUISA>Controle microbiano de pragas agrícolas</LINHA_DE_PESQUISA>
            <LINHA_DE_PESQUISA>Manejo integrado de doenças de plantas</LINHA_DE_PESQUISA>
         </PESQUISADOR>
         <PESQUISADOR NOME="Tereza Cristina de Assis" LATTES="3791371000725276" FORMACAO_ACADEMICA="Doutorado" CATEGORIA="PESQUISADOR">
            <AREA>Fitopatologia</AREA>
            <AREA>Micologia</AREA>
            <AREA>Parasitologia Agrícola</AREA>
            <GRUPO_DE_PESQUISA>Alimentação Saudável em Areas Urbanase Rurais - ASUR</GRUPO_DE_PESQUISA>
            <GRUPO_DE_PESQUISA>HORTALIÇAS</GRUPO_DE_PESQUISA>
            <LINHA_DE_PESQUISA>Fitossanidade</LINHA_DE_PESQUISA>
            <LINHA_DE_PESQUISA>Pesquisa-ação interdisciplinar e multi-atores</LINHA_DE_PESQUISA>
            <LINHA_DE_PESQUISA>Manejo integrado de doenças de plantas</LINHA_DE_PESQUISA>
         </PESQUISADOR>
         <PESQUISADOR NOME="Tereza Cristina de Assis" LATTES="3791371000725276" FORMACAO_ACADEMICA="Doutorado" CATEGORIA="PESQUISADOR">
            <AREA>Fitopatologia</AREA>
            <AREA>Micologia</AREA>
            <AREA>Parasitologia Agrícola</AREA>
            <GRUPO_DE_PESQUISA>Alimentação Saudável em Areas Urbanase Rurais - ASUR</GRUPO_DE_PESQUISA>
            <GRUPO_DE_PESQUISA>HORTALIÇAS</GRUPO_DE_PESQUISA>
            <LINHA_DE_PESQUISA>Fitossanidade</LINHA_DE_PESQUISA>
            <LINHA_DE_PESQUISA>Pesquisa-ação interdisciplinar e multi-atores</LINHA_DE_PESQUISA>
            <LINHA_DE_PESQUISA>Manejo integrado de doenças de plantas</LINHA_DE_PESQUISA>
         </PESQUISADOR>
      </PESQUISADORES>
      <LINHAS_DE_PESQUISA>
         <LINHA_DE_PESQUISA>
            <NOME>Pesquisa-ação interdisciplinar e multi-atores</NOME>
            <OBJETIVO>Estão envolvidos pesquisadores e extensionistas (engenheiros agrônomos, florestais, de pesca, climatologistas, sociólogos, economistas, geógrafos,etc.) com agricultores familiares organizados em Arranjos Produtivos Locais de base agroecológica em Pernambuco. Objetiva-se a construção e socialização de informações cientificas e tecnologias e, ao mesmo tempo a capacitação profissional, na prática de campo desses três atores. A ideia é cruzar conhecimentos científicos e saber local.</OBJETIVO>
            <SETOR_APLICACAO/>
            <SETOR_APLICACAO>Agricultura, Pecuária e Serviços Relacionados</SETOR_APLICACAO>
            <SETOR_APLICACAO>Recursos humanos</SETOR_APLICACAO>
         </LINHA_DE_PESQUISA>
      </LINHAS_DE_PESQUISA>
   </GRUPO_DE_PESQUISA>
</DIRETORIO_DE_GRUPOS>
